Metadata-Version: 1.0
Name: awsudacitycoursemax-distributions
Version: 0.1
Summary: Gaussian and binomial distributions
Home-page: UNKNOWN
Author: ['Maximilian Muench']
Author-email: UNKNOWN
License: UNKNOWN
Platform: UNKNOWN
